{
  "timestamp": "2026-01-20T23:27:50.485000",
  "agent_name": "Onboarding",
  "step": "end",
  "input_context": {
    "task": "onboarding",
    "user_id": "admin@admin.com",
    "request_id": "97d44c22-f000-4f3d-b7ec-874df205f9ab",
    "params": {
      "step": "analyze",
      "url": "https://specialistsupportservices.net.nz/"
    }
  },
  "output_result": {
    "status": "success",
    "data": {
      "identity": {
        "business_name": "Specialist Support Services (SSS)",
        "niche": "Bail & Parole Support",
        "phone": "021 280 6655",
        "email": "info@sss.net.nz",
        "address": "3 Glenside Crescent, Auckland 1010",
        "key_services": [
          "EM Bail Accommodation",
          "Parole Accommodation",
          "Rehabilitation Programmes",
          "Bail Application Assistance",
          "Escorted Attendance"
        ],
        "website": "https://specialistsupportservices.net.nz/"
      }
    },
    "message": "Analysis Complete",
    "timestamp": "2026-01-20 23:27:50.484810"
  },
  "error_traceback": null
}